{
    "term": "buddha",
    "meanings": [
        {
            "definition": "A title given to Siddhartha Gautama, the founder of Buddhism.",
            "pos": "noun",
            "sent1": "The buddha taught about peace and kindness.",
            "sent2": "People around the world respect the buddha for his wisdom.",
            "sent3": "I saw a small buddha statue that made me smile.",
            "sent4": "Her calm demeanor was like a buddha in the midst of chaos.",
            "sent5": "The image of the buddha sitting under the tree is serene."
        },
        {
            "definition": "A person who has attained enlightenment and is revered in Buddhism.",
            "pos": "noun",
            "sent1": "The buddha's teachings inspire many to seek inner peace.",
            "sent2": "In Buddhism, followers strive to be like the buddha.",
            "sent3": "I jokingly called my friend a buddha after he solved a difficult problem.",
            "sent4": "Her wisdom shone through her words, like a modern-day buddha.",
            "sent5": "The buddha's presence filled the room with tranquility."
        },
        {
            "definition": "A statue or image of the Buddha.",
            "pos": "noun",
            "sent1": "The buddha in the temple looked ancient and wise.",
            "sent2": "Tourists often take pictures with the buddha statues.",
            "sent3": "I accidentally knocked over a small buddha figurine in my room.",
            "sent4": "The golden buddha gleamed in the sunlight, captivating all who saw it.",
            "sent5": "The intricate details on the buddha sculpture were mesmerizing."
        }
    ]
}