{
    "term": "burials",
    "meanings": [
        {
            "definition": "The act of burying a dead body.",
            "pos": "noun",
            "sent1": "The burials took place at sunset.",
            "sent2": "The burials in the cemetery were solemn.",
            "sent3": "The burials were so quiet, even the birds seemed to pay their respects.",
            "sent4": "The burials were like seeds planted in the earth, waiting to bloom again.",
            "sent5": "The burials under the old oak tree were a peaceful sight."
        },
        {
            "definition": "The process or ceremony of burying a dead body.",
            "pos": "noun",
            "sent1": "During the burials, everyone wore black.",
            "sent2": "The burials were conducted with great care and respect.",
            "sent3": "The burials turned into a dance of remembrance under the moonlight.",
            "sent4": "The burials were a tapestry of traditions woven together.",
            "sent5": "The burials echoed with the whispers of those who had gone before."
        },
        {
            "definition": "The place where a dead body is buried.",
            "pos": "noun",
            "sent1": "The burials were marked by simple headstones.",
            "sent2": "The burials in the churchyard were well-tended.",
            "sent3": "The burials became a secret meeting place for the neighborhood cats.",
            "sent4": "The burials were a library of stories waiting to be read.",
            "sent5": "The burials overlooked a peaceful valley."
        }
    ]
}