{
    "term": "cives",
    "meanings": [
        {
            "definition": "A citizen or inhabitant of a city.",
            "pos": "noun",
            "sent1": "The cives gathered in the town square for the annual festival.",
            "sent2": "The cives of this city take pride in their community.",
            "sent3": "The cives decided to paint the town hall pink for a change.",
            "sent4": "The cives were the heartbeat of the bustling city.",
            "sent5": "The cives' loyalty to their city was unwavering."
        },
        {
            "definition": "A member of a community or society.",
            "pos": "noun",
            "sent1": "As a cives of the neighborhood, she always helped her neighbors in need.",
            "sent2": "The cives of the club met every Friday for their book discussions.",
            "sent3": "The cives organized a surprise party for their friend's birthday.",
            "sent4": "She was a dedicated cives of the local charity organization.",
            "sent5": "The cives worked together to improve their community park."
        },
        {
            "definition": "A person who is entitled to the rights and privileges of a particular country.",
            "pos": "noun",
            "sent1": "The cives proudly displayed their national flag on Independence Day.",
            "sent2": "All cives have the responsibility to uphold the laws of their country.",
            "sent3": "The cives celebrated their citizenship with a parade.",
            "sent4": "She was a grateful cives of her homeland.",
            "sent5": "The cives cherished their freedom and democracy."
        }
    ]
}