{
    "term": "clacked",
    "meanings": [
        {
            "definition": "Talk rapidly and continuously in a foolish, excited, or incomprehensible way.",
            "pos": "verb",
            "sent1": "She clacked on about her new favorite TV show.",
            "sent2": "The children clacked away, sharing stories and laughter.",
            "sent3": "His clacking about aliens visiting Earth made everyone chuckle.",
            "sent4": "Her heels clacked on the pavement as she hurried to catch the bus.",
            "sent5": "The gossiping birds clacked in the trees, spreading rumors."
        }
    ]
}