{
    "term": "coleorhizae",
    "meanings": [
        {
            "definition": "The outer covering of a seed, which is typically a protective sheath.",
            "pos": "noun",
            "sent1": "The coleorhizae of the seed helps protect it from harm.",
            "sent2": "The gardener carefully removed the coleorhizae before planting the seed.",
            "sent3": "The curious squirrel mistook the coleorhizae for a tasty snack.",
            "sent4": "The coleorhizae shielded the seed like a knight protecting a castle.",
            "sent5": "The shiny coleorhizae glistened in the sunlight, catching the eye of a passing bird."
        },
        {
            "definition": "The part of a seed that emerges first during germination, forming the root.",
            "pos": "noun",
            "sent1": "After planting the seed, the coleorhizae slowly began to grow downwards.",
            "sent2": "The tiny coleorhizae pushed through the soil in search of water and nutrients.",
            "sent3": "The impatient seedling complained that the coleorhizae was taking too long to reach the ground.",
            "sent4": "The coleorhizae delved deep into the earth, anchoring the plant firmly in place.",
            "sent5": "The coleorhizae eagerly stretched out, eager to establish a strong root system for the plant."
        }
    ]
}