{
    "term": "enframes",
    "meanings": [
        {
            "definition": "To enclose in or as if in a frame.",
            "pos": "verb",
            "sent1": "She enframes her favorite photo to protect it.",
            "sent2": "The artist enframes the painting with a beautiful wooden border.",
            "sent3": "He enframes his sandwich with extra lettuce for a fun twist.",
            "sent4": "The garden enframes the house like a colorful picture.",
            "sent5": "The window enframes the view of the mountains perfectly."
        },
        {
            "definition": "To surround or enclose something.",
            "pos": "verb",
            "sent1": "The garden enframes the house with blooming flowers.",
            "sent2": "The fence enframes the backyard, keeping it safe.",
            "sent3": "The cat enframes itself in a cozy box for a nap.",
            "sent4": "The darkness enframes the light like a mysterious cloak.",
            "sent5": "The frame enframes the artwork, highlighting its beauty."
        },
        {
            "definition": "To put into a frame or border.",
            "pos": "verb",
            "sent1": "She enframes the certificate to display it proudly.",
            "sent2": "The designer enframes the logo with a sleek black frame.",
            "sent3": "He enframes his words with humor to make them memorable.",
            "sent4": "The sky enframes the sunset in a breathtaking display.",
            "sent5": "The mirror enframes the reflection, creating a striking effect."
        }
    ]
}