{
    "term": "foulbrood",
    "meanings": [
        {
            "definition": "A disease affecting bee larvae, caused by bacteria.",
            "pos": "noun",
            "sent1": "The beekeeper was worried about the foulbrood spreading to other hives.",
            "sent2": "The foulbrood outbreak devastated the bee population in the area.",
            "sent3": "The bees had a meeting to discuss how to avoid catching foulbrood.",
            "sent4": "The foulbrood of negativity was infecting the once-happy community.",
            "sent5": "The foulbrood disease was like a silent killer among the bee larvae."
        },
        {
            "definition": "To spoil or ruin something.",
            "pos": "verb",
            "sent1": "Leaving the food out in the sun will foulbrood it quickly.",
            "sent2": "She accidentally foulbrooded the surprise by mentioning it too soon.",
            "sent3": "The mischievous squirrel tried to foulbrood the picnic by stealing all the sandwiches.",
            "sent4": "His negative attitude foulbrooded the mood of the party.",
            "sent5": "The rain threatened to foulbrood their plans for a day at the beach."
        }
    ]
}