{
    "term": "ipecacuanhas",
    "meanings": [
        {
            "definition": "A South American plant of the madder family, the root of which is used as an emetic.",
            "pos": "noun",
            "sent1": "The ipecacuanhas plant's root helps induce vomiting.",
            "sent2": "The doctor prescribed ipecacuanhas to treat food poisoning.",
            "sent3": "After taking ipecacuanhas, the patient felt relieved.",
            "sent4": "Her reaction to the news was like a sudden dose of ipecacuanhas.",
            "sent5": "The smell of ipecacuanhas lingered in the room, reminding him of his illness."
        },
        {
            "definition": "A medicinal preparation made from the dried roots of this plant.",
            "pos": "noun",
            "sent1": "The ipecacuanhas medicine is effective in treating certain conditions.",
            "sent2": "She bought ipecacuanhas from the pharmacy for her cough.",
            "sent3": "The children giggled at the taste of the ipecacuanhas syrup.",
            "sent4": "His words acted as ipecacuanhas, bringing out the truth.",
            "sent5": "The ipecacuanhas remedy worked wonders for her upset stomach."
        }
    ]
}