{
    "term": "legalities",
    "meanings": [
        {
            "definition": "The quality or state of being in accordance with the law.",
            "pos": "noun",
            "sent1": "Understanding the legalities is important to avoid trouble.",
            "sent2": "She made sure to check all the legalities before signing the contract.",
            "sent3": "The legalities of the situation were so clear, even a cat could understand.",
            "sent4": "Navigating the legalities felt like walking through a maze of rules.",
            "sent5": "The legalities of the case were as strict as a teacher with a ruler."
        },
        {
            "definition": "The legal aspects or requirements of a situation.",
            "pos": "noun",
            "sent1": "Dealing with the legalities can be time-consuming.",
            "sent2": "He hired a lawyer to handle all the legalities of the business deal.",
            "sent3": "The legalities seemed to dance around the room, making everyone dizzy.",
            "sent4": "She felt trapped in the web of legalities that surrounded her.",
            "sent5": "The legalities of the matter were as complex as a puzzle with missing pieces."
        }
    ]
}