{
    "term": "loutishly",
    "meanings": [
        {
            "definition": "In a rude or uncouth manner",
            "pos": "adverb",
            "sent1": "He spoke loutishly at the dinner table, causing discomfort to everyone.",
            "sent2": "She walked loutishly through the crowded room, bumping into people without apologizing.",
            "sent3": "The comedian loutishly imitated a clumsy dancer, making the audience burst into laughter.",
            "sent4": "His loutishly loud laughter echoed through the quiet library, drawing annoyed glances.",
            "sent5": "The toddler ran loutishly around the playground, knocking over toys in his path."
        },
        {
            "definition": "Behaving in a boorish or clumsy way",
            "pos": "adjective",
            "sent1": "The loutishly dressed man barged into the elegant party, spilling his drink on the host.",
            "sent2": "She found his loutishly written note on the table, filled with spelling mistakes and smudges.",
            "sent3": "The cat tried to balance on the loutishly stacked boxes, causing a hilarious tower collapse.",
            "sent4": "The old car moved loutishly down the road, emitting loud noises and leaving a trail of smoke.",
            "sent5": "The loutishly painted house stood out in the neighborhood, with mismatched colors and crooked lines."
        }
    ]
}