{
    "term": "lyart",
    "meanings": [
        {
            "definition": "Having a gray or white color, especially as a result of age or old age.",
            "pos": "adjective",
            "sent1": "The old cat had a lyart fur that shimmered in the sunlight.",
            "sent2": "The lyart clouds drifted lazily across the sky.",
            "sent3": "The lyart squirrel looked like a tiny wise elder in the park.",
            "sent4": "Her lyart hair was a crown of wisdom and experience.",
            "sent5": "The lyart mountains stood majestic and serene in the distance."
        },
        {
            "definition": "To become gray or white in color, especially as a result of age or old age.",
            "pos": "verb",
            "sent1": "Over time, his hair began to lyart at the temples.",
            "sent2": "The old building slowly lyarted as the paint peeled away.",
            "sent3": "The flowers in the garden seemed to lyart overnight, surprising everyone.",
            "sent4": "The memories of the past lyarted in his mind, fading but still present.",
            "sent5": "As the seasons changed, the leaves on the trees lyarted before falling."
        }
    ]
}