{
    "term": "medalling",
    "meanings": [
        {
            "definition": "To win a medal in a competition.",
            "pos": "verb",
            "sent1": "She was medalling in the swimming competition.",
            "sent2": "The athlete was medalling in the track and field event.",
            "sent3": "After medalling in the race, she proudly displayed her medal.",
            "sent4": "He kept medalling in various sports, showing his talent.",
            "sent5": "The feeling of medalling for the first time was exhilarating."
        },
        {
            "definition": "To award or present a medal to someone.",
            "pos": "verb",
            "sent1": "The coach was medalling the winners of the tournament.",
            "sent2": "They were medalling the top students at the academic ceremony.",
            "sent3": "The mayor was medalling the local heroes at the community event.",
            "sent4": "The organization was medalling outstanding volunteers for their service.",
            "sent5": "Medalling the champions was a highlight of the event."
        }
    ]
}