{
    "term": "muggurs",
    "meanings": [
        {
            "definition": "Muggurs (noun): A type of small, furry animal often found in forests.",
            "pos": "noun",
            "sent1": "I saw a cute muggurs playing in the woods.",
            "sent2": "The muggurs scurried up the tree to escape danger.",
            "sent3": "The mischievous muggurs stole my sandwich during the picnic.",
            "sent4": "The forest was alive with the chatter of muggurs.",
            "sent5": "The muggurs' fluffy tails swished as they ran through the underbrush."
        },
        {
            "definition": "Muggurs (verb): To steal or take something without permission.",
            "pos": "verb",
            "sent1": "He tried to muggurs some cookies from the jar.",
            "sent2": "She muggursed a glance at the secret document.",
            "sent3": "The raccoon muggursed the shiny object from the campsite.",
            "sent4": "The thief muggursed silently through the darkened room.",
            "sent5": "The pickpocket expertly muggursed the wallet from the distracted tourist."
        },
        {
            "definition": "Muggurs (adjective): Describing something that is dirty or grimy.",
            "pos": "adjective",
            "sent1": "The old shed had a muggurs appearance with its peeling paint.",
            "sent2": "She avoided the muggurs alley due to its unpleasant smell.",
            "sent3": "After playing in the mud, the kids were completely muggurs.",
            "sent4": "The abandoned house had a muggurs, neglected feel to it.",
            "sent5": "His hands were muggurs after working in the garden all day."
        }
    ]
}