{
    "term": "mulls",
    "meanings": [
        {
            "definition": "To think about carefully",
            "pos": "verb",
            "sent1": "She mulls over her choices before making a decision.",
            "sent2": "He often mulls about what to do next in his life.",
            "sent3": "As she mulls over the menu, her stomach growls impatiently.",
            "sent4": "The student mulls over the exam questions, trying to find the right answers.",
            "sent5": "The detective mulls over the clues, trying to solve the mystery."
        },
        {
            "definition": "To heat and spice (wine, cider, etc.)",
            "pos": "verb",
            "sent1": "Mom mulls the cider with cinnamon for a cozy drink.",
            "sent2": "The chef mulls the wine with cloves for a special recipe.",
            "sent3": "The aroma of mulling cider fills the kitchen with warmth.",
            "sent4": "The spices mull together in the pot, creating a delightful fragrance.",
            "sent5": "The family enjoys the mulling process, anticipating the delicious drink."
        },
        {
            "definition": "To grind (an ingredient) into powder",
            "pos": "verb",
            "sent1": "She mulls the herbs into a fine powder for the recipe.",
            "sent2": "The miller mulls the grains into flour for baking.",
            "sent3": "The kitchen is filled with the sound of mulling spices.",
            "sent4": "The mortar and pestle are used to mull the ingredients finely.",
            "sent5": "The baker carefully mulls the nuts to add flavor to the dish."
        }
    ]
}