{
    "term": "owly",
    "meanings": [
        {
            "definition": "Resembling an owl in appearance or behavior.",
            "pos": "adjective",
            "sent1": "The owly eyes of the stuffed owl made it look wise.",
            "sent2": "The girl's owly glasses gave her a scholarly look.",
            "sent3": "The owly hat on the scarecrow made the birds think it was real.",
            "sent4": "The old tree had an owly presence, standing tall and silent.",
            "sent5": "The painting captured the owly expression of the owl perfectly."
        },
        {
            "definition": "In a manner characteristic of an owl.",
            "pos": "adverb",
            "sent1": "She looked owly at the dark forest, feeling a bit scared.",
            "sent2": "The owl flew owly through the night, hunting for prey.",
            "sent3": "He moved owly through the room, trying not to make a sound.",
            "sent4": "The dancer moved owly across the stage, graceful and silent.",
            "sent5": "The wind whispered owly through the trees, like a ghostly owl."
        }
    ]
}