{
    "term": "panellist",
    "meanings": [
        {
            "definition": "A person who is a member of a panel.",
            "pos": "noun",
            "sent1": "The panellist shared their ideas during the panel discussion.",
            "sent2": "The panellist sat alongside other experts on the panel.",
            "sent3": "The panellist joked about needing a bigger chair on the panel.",
            "sent4": "The panellist's voice stood out like a soloist in a choir.",
            "sent5": "The panellist's insights shone brightly among the panelists."
        },
        {
            "definition": "One who participates in a panel discussion.",
            "pos": "noun",
            "sent1": "As a panellist, she contributed valuable opinions to the discussion.",
            "sent2": "The panellist listened attentively to the other speakers on the panel.",
            "sent3": "During the panel discussion, the panellist made a funny facial expression.",
            "sent4": "The panellist's words painted a vivid picture in the minds of the audience.",
            "sent5": "The panellist's presence added depth to the panel conversation."
        }
    ]
}