{
    "term": "parmigiano",
    "meanings": [
        {
            "definition": "A hard, dry, sharp-flavored Italian cheese made from skim milk.",
            "pos": "noun",
            "sent1": "I grated some parmigiano over my pasta for extra flavor.",
            "sent2": "The salad was topped with a sprinkle of parmigiano cheese.",
            "sent3": "The mouse tried to steal the parmigiano from the kitchen but got caught.",
            "sent4": "Her words were as sharp as a block of parmigiano.",
            "sent5": "The aroma of parmigiano filled the room, making everyone hungry."
        },
        {
            "definition": "A dish made with Parmesan cheese, typically referring to chicken or eggplant dishes.",
            "pos": "noun",
            "sent1": "I ordered the parmigiano chicken for dinner.",
            "sent2": "The parmigiano eggplant was a hit at the potluck.",
            "sent3": "The chef accidentally dropped the parmigiano dish, creating a cheesy mess.",
            "sent4": "Her smile was as comforting as a warm plate of parmigiano.",
            "sent5": "The aroma of parmigiano filled the room, making everyone hungry."
        }
    ]
}