{
    "term": "perjures",
    "meanings": [
        {
            "definition": "Tell a lie or lies under oath.",
            "pos": "verb",
            "sent1": "He perjures himself in court by not telling the truth.",
            "sent2": "She perjures when she swears to tell the whole truth.",
            "sent3": "The detective perjures about his alibi, but the evidence reveals the truth.",
            "sent4": "The politician perjures his promises to gain votes.",
            "sent5": "The witness perjures, causing a mistrial due to false testimony."
        },
        {
            "definition": "Willfully make a false statement while under oath.",
            "pos": "verb",
            "sent1": "The suspect perjures during the interrogation to mislead the police.",
            "sent2": "It is a crime to perjures in a court of law.",
            "sent3": "The student perjures about studying for the exam, but fails miserably.",
            "sent4": "The CEO perjures about the company's financial status to investors.",
            "sent5": "The defendant perjures, leading to his own downfall in the trial."
        }
    ]
}