{
    "term": "redtops",
    "meanings": [
        {
            "definition": "A type of newspaper known for sensationalism and tabloid-style reporting.",
            "pos": "noun",
            "sent1": "I saw some redtops at the store with eye-catching headlines.",
            "sent2": "The redtops often focus on celebrity gossip and scandals.",
            "sent3": "The redtops made me chuckle with their exaggerated stories.",
            "sent4": "She always takes the redtops with a grain of salt.",
            "sent5": "The redtops are like a guilty pleasure for many readers."
        },
        {
            "definition": "The top part of a plant that is red in color.",
            "pos": "noun",
            "sent1": "The redtops of the flowers brightened up the garden.",
            "sent2": "The redtops of the maple tree turned a vibrant shade in autumn.",
            "sent3": "The redtops swayed gently in the breeze, painting the garden red.",
            "sent4": "Her favorite part of the plant was always the redtops.",
            "sent5": "The redtops stood out like flames among the green leaves."
        },
        {
            "definition": "A type of grass commonly found in pastures and fields.",
            "pos": "noun",
            "sent1": "The cows grazed on the lush redtops in the field.",
            "sent2": "The redtops provided a soft bed for the rabbits to rest on.",
            "sent3": "The mischievous goats loved nibbling on the redtops.",
            "sent4": "The redtops swayed gracefully in the wind, a sea of red.",
            "sent5": "The redtops carpeted the meadow in a vibrant hue."
        }
    ]
}