{
    "term": "shopgirl",
    "meanings": [
        {
            "definition": "A woman who works in a shop.",
            "pos": "noun",
            "sent1": "The shopgirl helped customers find the right size of shoes.",
            "sent2": "The shopgirl greeted everyone with a smile as they entered the store.",
            "sent3": "The shopgirl accidentally mixed up the shoe sizes, causing a funny confusion.",
            "sent4": "Her mind was a shopgirl's display window, showcasing knowledge and helpfulness.",
            "sent5": "The shopgirl's presence in the store made it feel welcoming and friendly."
        },
        {
            "definition": "A female employee in a retail store.",
            "pos": "noun",
            "sent1": "As a shopgirl, she knew where every product was located in the store.",
            "sent2": "The shopgirl restocked the shelves with new merchandise every morning.",
            "sent3": "The shopgirl playfully pretended to be a mannequin in the store's window display.",
            "sent4": "Her laughter echoed through the store, brightening the day like a shopgirl's smile.",
            "sent5": "The shopgirl's efficiency and dedication were admired by her colleagues."
        }
    ]
}