{
    "term": "shophars",
    "meanings": [
        {
            "definition": "A type of musical instrument made from a ram's horn.",
            "pos": "noun",
            "sent1": "During the festival, the shophars echoed through the valley.",
            "sent2": "The musician played the shophars beautifully at the concert.",
            "sent3": "The shophars seemed to dance in the air as the music filled the room.",
            "sent4": "The shophars' melody carried the listeners to a different world.",
            "sent5": "The shophars' unique sound captivated everyone in the audience."
        },
        {
            "definition": "The sound produced by blowing into a shophar.",
            "pos": "noun",
            "sent1": "The shophars' call could be heard from afar.",
            "sent2": "The ancient shophars' sound was both haunting and beautiful.",
            "sent3": "The shophars' melody made the birds chirp along in harmony.",
            "sent4": "The shophars' echo lingered in the air long after the music stopped.",
            "sent5": "The shophars' notes resonated in the hearts of all who listened."
        },
        {
            "definition": "To play a shophar during religious ceremonies.",
            "pos": "verb",
            "sent1": "The priest shophars during the sacred ritual.",
            "sent2": "He shophars with reverence and skill at every ceremony.",
            "sent3": "The children giggled as he shophars in a playful tune.",
            "sent4": "She shophars with devotion, filling the temple with music.",
            "sent5": "The community gathers to hear him shophars in prayer."
        }
    ]
}