{
    "term": "silicon",
    "meanings": [
        {
            "definition": "A nonmetallic element with semiconducting properties, used in electronics.",
            "pos": "noun",
            "sent1": "The silicon in my phone helps it work smoothly.",
            "sent2": "The factory produces silicon chips for computers.",
            "sent3": "I accidentally dropped the silicon chip in my coffee!",
            "sent4": "Her mind was like a complex circuit board, each thought a tiny piece of silicon.",
            "sent5": "The silicon in the device glowed with a faint light, indicating it was on."
        },
        {
            "definition": "A chemical element with the symbol Si and atomic number 14.",
            "pos": "noun",
            "sent1": "Silicon is an essential element in many minerals.",
            "sent2": "The periodic table lists silicon as Si.",
            "sent3": "I mistook the silicon sample for sugar in the lab!",
            "sent4": "His words were like silicon, forming a strong foundation for their relationship.",
            "sent5": "The silicon in the rock sparkled in the sunlight, catching my eye."
        },
        {
            "definition": "A gray, crystalline solid used in making glass and ceramics.",
            "pos": "noun",
            "sent1": "The artist carefully added silicon to the glass mixture.",
            "sent2": "Silicon is a key ingredient in creating durable ceramics.",
            "sent3": "The mischievous child sprinkled silicon powder on the floor, pretending it was magic dust.",
            "sent4": "Her smile was as clear and strong as silicon, reflecting her inner strength.",
            "sent5": "The silicon in the vase gave it a beautiful, shiny finish."
        }
    ]
}