{
    "term": "troupial",
    "meanings": [
        {
            "definition": "A brightly colored bird native to South America.",
            "pos": "noun",
            "sent1": "The troupial sang a beautiful song in the forest.",
            "sent2": "I saw a troupial perched on a branch in the jungle.",
            "sent3": "The troupial tried to teach the parrot how to sing but failed.",
            "sent4": "Her dress was as vibrant as a troupial's feathers.",
            "sent5": "The troupial's orange and black feathers stood out against the green leaves."
        },
        {
            "definition": "A member of the icterid family.",
            "pos": "noun",
            "sent1": "The troupial and the blackbird were both icterids.",
            "sent2": "I learned that the troupial is a member of the icterid family.",
            "sent3": "The troupial joked with the grackle about family reunions.",
            "sent4": "His voice was as melodious as a troupial's call.",
            "sent5": "The troupial's family tree included many other icterids."
        },
        {
            "definition": "A type of oriole with a distinctive black and orange plumage.",
            "pos": "noun",
            "sent1": "The troupial's black and orange feathers were striking.",
            "sent2": "I spotted a troupial with its unique plumage in the tree.",
            "sent3": "The troupial and the oriole had a fashion face-off.",
            "sent4": "Her hair was styled in a way that resembled a troupial's colors.",
            "sent5": "The troupial's plumage was a bold statement in the aviary."
        }
    ]
}